hardware/sovereign_ledger_validator.v
/*
 * ∴ SOVEREIGN LEDGER VALIDATOR v1.0
 * Law Ω₀: Silicon Truth
 * 
 * Synthesizable RTL for deterministic ledger verification.
 * Target: Lattice iCE40 / Xilinx Artix-7
 * Reality Level: C5-REAL
 */

module sovereign_ledger_validator #(
    parameter HASH_WIDTH = 256
)(
    input wire clk,
    input wire rst_n,
    
    // Control
    input wire start_validation,
    input wire [31:0] entropy_injection,
    
    // Inputs
    input wire [HASH_WIDTH-1:0] prev_hash_in,
    input wire [HASH_WIDTH-1:0] hash_in,
    input wire [31:0] actor_permissions,
    input wire [31:0] required_permissions,
    
    // Outputs
    output reg done,
    output reg valid,
    output reg [3:0] status_code,
    output reg [31:0] validated_event_count,
    
    // Error Flags
    output reg chain_error,
    output reg hash_error,
    output reg permission_error,
    output reg entropy_alarm
);

    // States
    localparam STATE_IDLE         = 4'h0;
    localparam STATE_LATCH        = 4'h1;
    localparam STATE_VERIFY_CHAIN = 4'h2;
    localparam STATE_VERIFY_HASH  = 4'h3;
    localparam STATE_VERIFY_PERM  = 4'h4;
    localparam STATE_COMMIT       = 4'h5;
    localparam STATE_DONE         = 4'h6;
    localparam STATE_CHAIN_ERR    = 4'h8;
    localparam STATE_HASH_ERR     = 4'h9;
    localparam STATE_PERM_ERR     = 4'hA;
    localparam STATE_ENTROPY_ERR  = 4'hB;

    reg [HASH_WIDTH-1:0] last_valid_hash;
    reg [HASH_WIDTH-1:0] prev_hash_r;
    reg [HASH_WIDTH-1:0] hash_r;
    reg [31:0] actor_permissions_r;
    reg [31:0] required_permissions_r;
    reg [31:0] entropy_injection_r;
    
    reg [3:0] state;

    always @(posedge clk or negedge rst_n) begin
        if (!rst_n) begin
            state <= STATE_IDLE;
            last_valid_hash <= {HASH_WIDTH{1'b0}};
            prev_hash_r <= {HASH_WIDTH{1'b0}};
            hash_r <= {HASH_WIDTH{1'b0}};
            actor_permissions_r <= 32'h0;
            required_permissions_r <= 32'h0;
            entropy_injection_r <= 32'h0;
            
            done <= 1'b0;
            valid <= 1'b0;
            status_code <= STATE_IDLE;
            validated_event_count <= 32'h0;
            
            chain_error <= 1'b0;
            hash_error <= 1'b0;
            permission_error <= 1'b0;
            entropy_alarm <= 1'b0;
        end else begin
            status_code <= state;
            case (state)
                STATE_IDLE: begin
                    done <= 1'b0;
                    valid <= 1'b0;
                    chain_error <= 1'b0;
                    hash_error <= 1'b0;
                    permission_error <= 1'b0;
                    entropy_alarm <= 1'b0;
                    if (start_validation) begin
                        state <= STATE_LATCH;
                        prev_hash_r <= prev_hash_in;
                        hash_r <= hash_in;
                        actor_permissions_r <= actor_permissions;
                        required_permissions_r <= required_permissions;
                        entropy_injection_r <= entropy_injection;
                    end
                end
                
                STATE_LATCH: begin
                    if (entropy_injection_r == 32'hFFFFFFFF) begin
                        entropy_alarm <= 1'b1;
                        state <= STATE_ENTROPY_ERR;
                    end else begin
                        state <= STATE_VERIFY_CHAIN;
                    end
                end
                
                STATE_VERIFY_CHAIN: begin
                    if (validated_event_count > 0 && prev_hash_r != last_valid_hash) begin
                        chain_error <= 1'b1;
                        state <= STATE_CHAIN_ERR;
                    end else begin
                        state <= STATE_VERIFY_HASH;
                    end
                end
                
                STATE_VERIFY_HASH: begin
                    if (hash_r == {HASH_WIDTH{1'b0}} || hash_r == {HASH_WIDTH{1'b1}}) begin
                        hash_error <= 1'b1;
                        state <= STATE_HASH_ERR;
                    end else begin
                        state <= STATE_VERIFY_PERM;
                    end
                end
                
                STATE_VERIFY_PERM: begin
                    if ((actor_permissions_r & required_permissions_r) != required_permissions_r) begin
                        permission_error <= 1'b1;
                        state <= STATE_PERM_ERR;
                    end else begin
                        state <= STATE_COMMIT;
                    end
                end
                
                STATE_COMMIT: begin
                    last_valid_hash <= hash_r;
                    validated_event_count <= validated_event_count + 1;
                    valid <= 1'b1;
                    state <= STATE_DONE;
                end
                
                STATE_DONE: begin
                    done <= 1'b1;
                    state <= STATE_IDLE;
                end
                
                STATE_CHAIN_ERR, STATE_HASH_ERR, STATE_PERM_ERR, STATE_ENTROPY_ERR: begin
                    valid <= 1'b0;
                    done <= 1'b1;
                    state <= STATE_IDLE;
                end
                
                default: state <= STATE_IDLE;
            endcase
        end
    end

endmodule

hardware/stress_tb.v
/*
 * ∴ SOVEREIGN LEDGER VALIDATOR TESTBENCH v1.2
 * Verifies Silicon Truth Invariants & Entropy Immunity (LGD-200)
 */

`timescale 1ns/1ps

module stress_tb;
    parameter HASH_WIDTH = 256;
    
    reg clk;
    reg rst_n;
    reg start_validation;
    reg [31:0] entropy_injection;
    reg [HASH_WIDTH-1:0] prev_hash_in;
    reg [HASH_WIDTH-1:0] hash_in;
    reg [31:0] actor_permissions;
    reg [31:0] required_permissions;
    
    wire done;
    wire valid;
    wire [3:0] status_code;
    wire [31:0] validated_event_count;
    wire chain_error;
    wire hash_error;
    wire permission_error;
    wire entropy_alarm;
    
    // Instantiate UUT
    sovereign_ledger_validator #(
        .HASH_WIDTH(HASH_WIDTH)
    ) uut (
        .clk(clk),
        .rst_n(rst_n),
        .start_validation(start_validation),
        .entropy_injection(entropy_injection),
        .prev_hash_in(prev_hash_in),
        .hash_in(hash_in),
        .actor_permissions(actor_permissions),
        .required_permissions(required_permissions),
        .done(done),
        .valid(valid),
        .status_code(status_code),
        .validated_event_count(validated_event_count),
        .chain_error(chain_error),
        .hash_error(hash_error),
        .permission_error(permission_error),
        .entropy_alarm(entropy_alarm)
    );

    // Clock generation: 100MHz (10ns period)
    initial clk = 0;
    always #5 clk = ~clk;
    
    // Debugging trace
    always @(posedge clk) begin
        $display("[TB TRACE] Time=%0t clk=%b rst_n=%b start=%b state=%h done=%b valid=%b count=%d error=%b alarm=%b",
                 $time, clk, rst_n, start_validation, status_code, done, valid, validated_event_count,
                 (chain_error || hash_error || permission_error), entropy_alarm);
    end

    initial begin
        $dumpfile("hardware/stress_tb.vcd");
        $dumpvars(0, stress_tb);
    end

    // Helper task to pulse start_validation cleanly
    task trigger_validation;
        begin
            @(posedge clk);
            #1;
            start_validation = 1;
            @(posedge clk);
            #1;
            start_validation = 0;
        end
    endtask

    // Capture registers for outputs sampled exactly on the done clock edge
    reg test_valid;
    reg [31:0] test_count;
    reg test_chain_error;
    reg test_hash_error;
    reg test_permission_error;
    reg test_entropy_alarm;

    // Tasks for validating
    task wait_done;
        begin
            @(posedge clk);
            while (!done) @(posedge clk);
            // Capture output state at the posedge where done is high
            test_valid = valid;
            test_count = validated_event_count;
            test_chain_error = chain_error;
            test_hash_error = hash_error;
            test_permission_error = permission_error;
            test_entropy_alarm = entropy_alarm;
            #1; // slight offset to clear task state safely
        end
    endtask
    
    integer passes = 0;
    integer failures = 0;
    
    initial begin
        $display("  ∴ INITIATING LGD-200 SILICON STRESS TEST...");
        
        // Reset state
        rst_n = 0;
        start_validation = 0;
        entropy_injection = 32'h0;
        prev_hash_in = 256'h0;
        hash_in = 256'h0;
        actor_permissions = 32'h0;
        required_permissions = 32'h0;
        
        #25;
        rst_n = 1;
        #15;
        
        // ==========================================
        // TEST 1: Genesis block validation (passes)
        // ==========================================
        #1;
        prev_hash_in = 256'h0000000000000000000000000000000000000000000000000000000000000000;
        hash_in      = 256'hAAAA111100000000000000000000000000000000000000000000000000000000;
        actor_permissions = 32'h00000001;
        required_permissions = 32'h00000001;
        entropy_injection = 32'h0;
        
        trigger_validation();
        wait_done();
        
        if (test_valid == 1 && test_count == 1 && test_chain_error == 0 && test_hash_error == 0 && test_permission_error == 0 && test_entropy_alarm == 0) begin
            $display("  [✓] TEST 1 PASS: Genesis block validated successfully.");
            passes = passes + 1;
        end else begin
            $display("  [✗] TEST 1 FAIL: Genesis validation failed. count=%d, valid=%b", test_count, test_valid);
            failures = failures + 1;
        end
        #10;

        // ==========================================
        // TEST 2: Sequential block 1 validation (passes)
        // ==========================================
        #1;
        prev_hash_in = 256'hAAAA111100000000000000000000000000000000000000000000000000000000;
        hash_in      = 256'hBBBB222200000000000000000000000000000000000000000000000000000000;
        actor_permissions = 32'h00000001;
        required_permissions = 32'h00000001;
        
        trigger_validation();
        wait_done();
        
        if (test_valid == 1 && test_count == 2 && test_chain_error == 0) begin
            $display("  [✓] TEST 2 PASS: Sequential block 1 verified.");
            passes = passes + 1;
        end else begin
            $display("  [✗] TEST 2 FAIL: Seq 1 verification failed.");
            failures = failures + 1;
        end
        #10;

        // ==========================================
        // TEST 3: Sequential block 2 validation (passes)
        // ==========================================
        #1;
        prev_hash_in = 256'hBBBB222200000000000000000000000000000000000000000000000000000000;
        hash_in      = 256'hCCCC333300000000000000000000000000000000000000000000000000000000;
        actor_permissions = 32'h00000001;
        required_permissions = 32'h00000001;
        
        trigger_validation();
        wait_done();
        
        if (test_valid == 1 && test_count == 3 && test_chain_error == 0) begin
            $display("  [✓] TEST 3 PASS: Sequential block 2 verified.");
            passes = passes + 1;
        end else begin
            $display("  [✗] TEST 3 FAIL: Seq 2 verification failed.");
            failures = failures + 1;
        end
        #10;

        // ==========================================
        // TEST 4: Broken chain linkage validation (chain_error)
        // ==========================================
        #1;
        prev_hash_in = 256'hDEADBEEF00000000000000000000000000000000000000000000000000000000; // mismatch
        hash_in      = 256'hDDDD444400000000000000000000000000000000000000000000000000000000;
        actor_permissions = 32'h00000001;
        required_permissions = 32'h00000001;
        
        trigger_validation();
        wait_done();
        
        if (test_valid == 0 && test_chain_error == 1 && test_count == 3) begin
            $display("  [✓] TEST 4 PASS: Broken chain link correctly detected & rejected.");
            passes = passes + 1;
        end else begin
            $display("  [✗] TEST 4 FAIL: Broken link check bypassed! valid=%b, chain_err=%b", test_valid, test_chain_error);
            failures = failures + 1;
        end
        #10;

        // ==========================================
        // TEST 5: Recovery test (passes)
        // ==========================================
        #1;
        prev_hash_in = 256'hCCCC333300000000000000000000000000000000000000000000000000000000; // correct
        hash_in      = 256'hDDDD444400000000000000000000000000000000000000000000000000000000;
        actor_permissions = 32'h00000001;
        required_permissions = 32'h00000001;
        
        trigger_validation();
        wait_done();
        
        if (test_valid == 1 && test_count == 4 && test_chain_error == 0) begin
            $display("  [✓] TEST 5 PASS: Validator successfully recovered chain linkage.");
            passes = passes + 1;
        end else begin
            $display("  [✗] TEST 5 FAIL: Recovery failed.");
            failures = failures + 1;
        end
        #10;

        // ==========================================
        // TEST 6: Permission check pass (passes)
        // ==========================================
        #1;
        prev_hash_in = 256'hDDDD444400000000000000000000000000000000000000000000000000000000;
        hash_in      = 256'hEEEE555500000000000000000000000000000000000000000000000000000000;
        actor_permissions = 32'h0000FFFF;
        required_permissions = 32'h000000FF;
        
        trigger_validation();
        wait_done();
        
        if (test_valid == 1 && test_count == 5 && test_permission_error == 0) begin
            $display("  [✓] TEST 6 PASS: Multi-bit permission verification succeeded.");
            passes = passes + 1;
        end else begin
            $display("  [✗] TEST 6 FAIL: Perm check pass failed.");
            failures = failures + 1;
        end
        #10;

        // ==========================================
        // TEST 7: Permission check fail (permission_error)
        // ==========================================
        #1;
        prev_hash_in = 256'hEEEE555500000000000000000000000000000000000000000000000000000000;
        hash_in      = 256'hFFFF666600000000000000000000000000000000000000000000000000000000;
        actor_permissions = 32'h0000007F; // Lacks 32'h00000080 bit
        required_permissions = 32'h000000FF;
        
        trigger_validation();
        wait_done();
        
        if (test_valid == 0 && test_permission_error == 1 && test_count == 5) begin
            $display("  [✓] TEST 7 PASS: Insufficient actor permission detected & rejected.");
            passes = passes + 1;
        end else begin
            $display("  [✗] TEST 7 FAIL: Security permission check bypassed.");
            failures = failures + 1;
        end
        #10;

        // ==========================================
        // TEST 8: Corrupt hash validation (hash_error)
        // ==========================================
        #1;
        prev_hash_in = 256'hEEEE555500000000000000000000000000000000000000000000000000000000;
        hash_in      = 256'h0000000000000000000000000000000000000000000000000000000000000000; // corrupt all-zero hash
        actor_permissions = 32'h0000FFFF;
        required_permissions = 32'h00000000;
        
        trigger_validation();
        wait_done();
        
        if (test_valid == 0 && test_hash_error == 1 && test_count == 5) begin
            $display("  [✓] TEST 8 PASS: Malformed zero-hash block detected & rejected.");
            passes = passes + 1;
        end else begin
            $display("  [✗] TEST 8 FAIL: Zero-hash block accepted.");
            failures = failures + 1;
        end
        #10;

        // ==========================================
        // TEST 9: Maximum entropy injection (entropy_alarm)
        // ==========================================
        #1;
        prev_hash_in = 256'hEEEE555500000000000000000000000000000000000000000000000000000000;
        hash_in      = 256'hFFFF777700000000000000000000000000000000000000000000000000000000;
        actor_permissions = 32'hFFFFFFFF;
        required_permissions = 32'h00000000;
        entropy_injection = 32'hFFFFFFFF; // entropy injection trigger
        
        trigger_validation();
        wait_done();
        
        if (test_valid == 0 && test_entropy_alarm == 1 && test_count == 5) begin
            $display("  [✓] TEST 9 PASS: Entropy Injection (32'hFFFFFFFF) triggered alarm & lockout.");
            passes = passes + 1;
        end else begin
            $display("  [✗] TEST 9 FAIL: Entropy injection ignored.");
            failures = failures + 1;
        end
        #10;

        // ==========================================
        // TEST 10: Mid-flight Reset Recovery (passes)
        // ==========================================
        #1;
        prev_hash_in = 256'hEEEE555500000000000000000000000000000000000000000000000000000000;
        hash_in      = 256'hFFFF888800000000000000000000000000000000000000000000000000000000;
        actor_permissions = 32'h00000001;
        required_permissions = 32'h00000001;
        entropy_injection = 32'h0;
        
        // Start validation sequence
        @(posedge clk);
        #1;
        start_validation = 1;
        @(posedge clk);
        #1;
        start_validation = 0;
        
        // Wait 2 clock cycles and assert reset
        @(posedge clk);
        @(posedge clk);
        #1;
        rst_n = 0;
        #25;
        rst_n = 1;
        #15;
        
        // Retry valid block validation
        trigger_validation();
        wait_done();
        
        if (test_valid == 1 && test_count == 1) begin
            $display("  [✓] TEST 10 PASS: Mid-flight reset recovery verified.");
            passes = passes + 1;
        end else begin
            $display("  [✗] TEST 10 FAIL: Mid-flight reset recovery failed. count=%d", test_count);
            failures = failures + 1;
        end
        #10;

        // Final Report
        $display("\n  ∴ SILICON VERIFICATION SUMMARY:");
        $display("    PASSES:   %0d", passes);
        $display("    FAILURES: %0d", failures);
        
        if (failures == 0 && passes == 10) begin
            $display("  ∴ [SYSTEM CONFIRMED] Sovereign Ledger Validator has attained absolute entropy immunity.");
        end else begin
            $display("  ∴ [INTEGRITY BREACH] Stress test failures detected!");
        end
        
        $finish;
    end

endmodule

hardware/stress_tb.vcd
$date
	Fri May 22 03:57:52 2026
$end
$version
	Icarus Verilog
$end
$timescale
	1ps
$end
$scope module stress_tb $end
$var wire 32 ! validated_event_count [31:0] $end
$var wire 1 " valid $end
$var wire 4 # status_code [3:0] $end
$var wire 1 $ permission_error $end
$var wire 1 % hash_error $end
$var wire 1 & entropy_alarm $end
$var wire 1 ' done $end
$var wire 1 ( chain_error $end
$var parameter 32 ) HASH_WIDTH $end
$var reg 32 * actor_permissions [31:0] $end
$var reg 1 + clk $end
$var reg 32 , entropy_injection [31:0] $end
$var reg 256 - hash_in [255:0] $end
$var reg 256 . prev_hash_in [255:0] $end
$var reg 32 / required_permissions [31:0] $end
$var reg 1 0 rst_n $end
$var reg 1 1 start_validation $end
$var reg 1 2 test_chain_error $end
$var reg 32 3 test_count [31:0] $end
$var reg 1 4 test_entropy_alarm $end
$var reg 1 5 test_hash_error $end
$var reg 1 6 test_permission_error $end
$var reg 1 7 test_valid $end
$var integer 32 8 failures [31:0] $end
$var integer 32 9 passes [31:0] $end
$scope module uut $end
$var wire 32 : actor_permissions [31:0] $end
$var wire 1 + clk $end
$var wire 32 ; entropy_injection [31:0] $end
$var wire 256 < hash_in [255:0] $end
$var wire 256 = prev_hash_in [255:0] $end
$var wire 32 > required_permissions [31:0] $end
$var wire 1 0 rst_n $end
$var wire 1 1 start_validation $end
$var parameter 32 ? HASH_WIDTH $end
$var parameter 4 @ STATE_CHAIN_ERR $end
$var parameter 4 A STATE_COMMIT $end
$var parameter 4 B STATE_DONE $end
$var parameter 4 C STATE_ENTROPY_ERR $end
$var parameter 4 D STATE_HASH_ERR $end
$var parameter 4 E STATE_IDLE $end
$var parameter 4 F STATE_LATCH $end
$var parameter 4 G STATE_PERM_ERR $end
$var parameter 4 H STATE_VERIFY_CHAIN $end
$var parameter 4 I STATE_VERIFY_HASH $end
$var parameter 4 J STATE_VERIFY_PERM $end
$var reg 32 K actor_permissions_r [31:0] $end
$var reg 1 ( chain_error $end
$var reg 1 ' done $end
$var reg 1 & entropy_alarm $end
$var reg 32 L entropy_injection_r [31:0] $end
$var reg 1 % hash_error $end
$var reg 256 M hash_r [255:0] $end
$var reg 256 N last_valid_hash [255:0] $end
$var reg 1 $ permission_error $end
$var reg 256 O prev_hash_r [255:0] $end
$var reg 32 P required_permissions_r [31:0] $end
$var reg 4 Q state [3:0] $end
$var reg 4 R status_code [3:0] $end
$var reg 1 " valid $end
$var reg 32 S validated_event_count [31:0] $end
$upscope $end
$scope task trigger_validation $end
$upscope $end
$scope task wait_done $end
$upscope $end
$upscope $end
$enddefinitions $end
$comment Show the parameter values. $end
$dumpall
b100 J
b11 I
b10 H
b1010 G
b1 F
b0 E
b1001 D
b1011 C
b110 B
b101 A
b1000 @
b100000000 ?
b100000000 )
$end
#0
$dumpvars
b0 S
b0 R
b0 Q
b0 P
b0 O
b0 N
b0 M
b0 L
b0 K
b0 >
b0 =
b0 <
b0 ;
b0 :
b0 9
b0 8
x7
x6
x5
x4
bx 3
x2
01
00
b0 /
b0 .
b0 -
b0 ,
0+
b0 *
0(
0'
0&
0%
0$
b0 #
0"
b0 !
$end
#5000
1+
#10000
0+
#15000
1+
#20000
0+
#25000
1+
10
#30000
0+
#35000
1+
#40000
0+
#41000
b1 /
b1 >
b1 *
b1 :
b1010101010101010000100010001000100000000000000000000000000000000000000000000000000000000000000000000000000000000000000000000000000000000000000000000000000000000000000000000000000000000000000000000000000000000000000000000000000000000000000000000000000000000 -
b1010101010101010000100010001000100000000000000000000000000000000000000000000000000000000000000000000000000000000000000000000000000000000000000000000000000000000000000000000000000000000000000000000000000000000000000000000000000000000000000000000000000000000 <
#45000
1+
#46000
11
#50000
0+
#55000
b1 P
b1 K
b1010101010101010000100010001000100000000000000000000000000000000000000000000000000000000000000000000000000000000000000000000000000000000000000000000000000000000000000000000000000000000000000000000000000000000000000000000000000000000000000000000000000000000 M
b1 Q
1+
#56000
01
#60000
0+
#65000
b10 Q
b1 #
b1 R
1+
#70000
0+
#75000
b11 Q
b10 #
b10 R
1+
#80000
0+
#85000
b100 Q
b11 #
b11 R
1+
#90000
0+
#95000
b101 Q
b100 #
b100 R
1+
#100000
0+
#105000
b110 Q
1"
b1 !
b1 S
b1010101010101010000100010001000100000000000000000000000000000000000000000000000000000000000000000000000000000000000000000000000000000000000000000000000000000000000000000000000000000000000000000000000000000000000000000000000000000000000000000000000000000000 N
b101 #
b101 R
1+
#110000
0+
#115000
b0 Q
1'
b110 #
b110 R
1+
#120000
0+
#125000
0"
0'
b0 #
b0 R
04
06
05
02
b1 3
17
1+
#126000
b1 9
#130000
0+
#135000
1+
#137000
b1011101110111011001000100010001000000000000000000000000000000000000000000000000000000000000000000000000000000000000000000000000000000000000000000000000000000000000000000000000000000000000000000000000000000000000000000000000000000000000000000000000000000000 -
b1011101110111011001000100010001000000000000000000000000000000000000000000000000000000000000000000000000000000000000000000000000000000000000000000000000000000000000000000000000000000000000000000000000000000000000000000000000000000000000000000000000000000000 <
b1010101010101010000100010001000100000000000000000000000000000000000000000000000000000000000000000000000000000000000000000000000000000000000000000000000000000000000000000000000000000000000000000000000000000000000000000000000000000000000000000000000000000000 .
b1010101010101010000100010001000100000000000000000000000000000000000000000000000000000000000000000000000000000000000000000000000000000000000000000000000000000000000000000000000000000000000000000000000000000000000000000000000000000000000000000000000000000000 =
#140000
0+
#145000
1+
#146000
11
#150000
0+
#155000
b1011101110111011001000100010001000000000000000000000000000000000000000000000000000000000000000000000000000000000000000000000000000000000000000000000000000000000000000000000000000000000000000000000000000000000000000000000000000000000000000000000000000000000 M
b1010101010101010000100010001000100000000000000000000000000000000000000000000000000000000000000000000000000000000000000000000000000000000000000000000000000000000000000000000000000000000000000000000000000000000000000000000000000000000000000000000000000000000 O
b1 Q
1+
#156000
01
#160000
0+
#165000
b10 Q
b1 #
b1 R
1+
#170000
0+
#175000
b11 Q
b10 #
b10 R
1+
#180000
0+
#185000
b100 Q
b11 #
b11 R
1+
#190000
0+
#195000
b101 Q
b100 #
b100 R
1+
#200000
0+
#205000
b110 Q
1"
b10 !
b10 S
b1011101110111011001000100010001000000000000000000000000000000000000000000000000000000000000000000000000000000000000000000000000000000000000000000000000000000000000000000000000000000000000000000000000000000000000000000000000000000000000000000000000000000000 N
b101 #
b101 R
1+
#210000
0+
#215000
b0 Q
1'
b110 #
b110 R
1+
#220000
0+
#225000
0"
0'
b0 #
b0 R
b10 3
1+
#226000
b10 9
#230000
0+
#235000
1+
#237000
b1100110011001100001100110011001100000000000000000000000000000000000000000000000000000000000000000000000000000000000000000000000000000000000000000000000000000000000000000000000000000000000000000000000000000000000000000000000000000000000000000000000000000000 -
b1100110011001100001100110011001100000000000000000000000000000000000000000000000000000000000000000000000000000000000000000000000000000000000000000000000000000000000000000000000000000000000000000000000000000000000000000000000000000000000000000000000000000000 <
b1011101110111011001000100010001000000000000000000000000000000000000000000000000000000000000000000000000000000000000000000000000000000000000000000000000000000000000000000000000000000000000000000000000000000000000000000000000000000000000000000000000000000000 .
b1011101110111011001000100010001000000000000000000000000000000000000000000000000000000000000000000000000000000000000000000000000000000000000000000000000000000000000000000000000000000000000000000000000000000000000000000000000000000000000000000000000000000000 =
#240000
0+
#245000
1+
#246000
11
#250000
0+
#255000
b1100110011001100001100110011001100000000000000000000000000000000000000000000000000000000000000000000000000000000000000000000000000000000000000000000000000000000000000000000000000000000000000000000000000000000000000000000000000000000000000000000000000000000 M
b1011101110111011001000100010001000000000000000000000000000000000000000000000000000000000000000000000000000000000000000000000000000000000000000000000000000000000000000000000000000000000000000000000000000000000000000000000000000000000000000000000000000000000 O
b1 Q
1+
#256000
01
#260000
0+
#265000
b10 Q
b1 #
b1 R
1+
#270000
0+
#275000
b11 Q
b10 #
b10 R
1+
#280000
0+
#285000
b100 Q
b11 #
b11 R
1+
#290000
0+
#295000
b101 Q
b100 #
b100 R
1+
#300000
0+
#305000
b110 Q
1"
b11 !
b11 S
b1100110011001100001100110011001100000000000000000000000000000000000000000000000000000000000000000000000000000000000000000000000000000000000000000000000000000000000000000000000000000000000000000000000000000000000000000000000000000000000000000000000000000000 N
b101 #
b101 R
1+
#310000
0+
#315000
b0 Q
1'
b110 #
b110 R
1+
#320000
0+
#325000
0"
0'
b0 #
b0 R
b11 3
1+
#326000
b11 9
#330000
0+
#335000
1+
#337000
b1101110111011101010001000100010000000000000000000000000000000000000000000000000000000000000000000000000000000000000000000000000000000000000000000000000000000000000000000000000000000000000000000000000000000000000000000000000000000000000000000000000000000000 -
b1101110111011101010001000100010000000000000000000000000000000000000000000000000000000000000000000000000000000000000000000000000000000000000000000000000000000000000000000000000000000000000000000000000000000000000000000000000000000000000000000000000000000000 <
b1101111010101101101111101110111100000000000000000000000000000000000000000000000000000000000000000000000000000000000000000000000000000000000000000000000000000000000000000000000000000000000000000000000000000000000000000000000000000000000000000000000000000000 .
b1101111010101101101111101110111100000000000000000000000000000000000000000000000000000000000000000000000000000000000000000000000000000000000000000000000000000000000000000000000000000000000000000000000000000000000000000000000000000000000000000000000000000000 =
#340000
0+
#345000
1+
#346000
11
#350000
0+
#355000
b1101110111011101010001000100010000000000000000000000000000000000000000000000000000000000000000000000000000000000000000000000000000000000000000000000000000000000000000000000000000000000000000000000000000000000000000000000000000000000000000000000000000000000 M
b1101111010101101101111101110111100000000000000000000000000000000000000000000000000000000000000000000000000000000000000000000000000000000000000000000000000000000000000000000000000000000000000000000000000000000000000000000000000000000000000000000000000000000 O
b1 Q
1+
#356000
01
#360000
0+
#365000
b10 Q
b1 #
b1 R
1+
#370000
0+
#375000
b1000 Q
1(
b10 #
b10 R
1+
#380000
0+
#385000
b0 Q
1'
b1000 #
b1000 R
1+
#390000
0+
#395000
0(
0'
b0 #
b0 R
12
07
1+
#396000
b100 9
#400000
0+
#405000
1+
#407000
b1100110011001100001100110011001100000000000000000000000000000000000000000000000000000000000000000000000000000000000000000000000000000000000000000000000000000000000000000000000000000000000000000000000000000000000000000000000000000000000000000000000000000000 .
b1100110011001100001100110011001100000000000000000000000000000000000000000000000000000000000000000000000000000000000000000000000000000000000000000000000000000000000000000000000000000000000000000000000000000000000000000000000000000000000000000000000000000000 =
#410000
0+
#415000
1+
#416000
11
#420000
0+
#425000
b1100110011001100001100110011001100000000000000000000000000000000000000000000000000000000000000000000000000000000000000000000000000000000000000000000000000000000000000000000000000000000000000000000000000000000000000000000000000000000000000000000000000000000 O
b1 Q
1+
#426000
01
#430000
0+
#435000
b10 Q
b1 #
b1 R
1+
#440000
0+
#445000
b11 Q
b10 #
b10 R
1+
#450000
0+
#455000
b100 Q
b11 #
b11 R
1+
#460000
0+
#465000
b101 Q
b100 #
b100 R
1+
#470000
0+
#475000
b110 Q
1"
b100 !
b100 S
b1101110111011101010001000100010000000000000000000000000000000000000000000000000000000000000000000000000000000000000000000000000000000000000000000000000000000000000000000000000000000000000000000000000000000000000000000000000000000000000000000000000000000000 N
b101 #
b101 R
1+
#480000
0+
#485000
b0 Q
1'
b110 #
b110 R
1+
#490000
0+
#495000
0"
0'
b0 #
b0 R
02
b100 3
17
1+
#496000
b101 9
#500000
0+
#505000
1+
#507000
b11111111 /
b11111111 >
b1111111111111111 *
b1111111111111111 :
b1110111011101110010101010101010100000000000000000000000000000000000000000000000000000000000000000000000000000000000000000000000000000000000000000000000000000000000000000000000000000000000000000000000000000000000000000000000000000000000000000000000000000000 -
b1110111011101110010101010101010100000000000000000000000000000000000000000000000000000000000000000000000000000000000000000000000000000000000000000000000000000000000000000000000000000000000000000000000000000000000000000000000000000000000000000000000000000000 <
b1101110111011101010001000100010000000000000000000000000000000000000000000000000000000000000000000000000000000000000000000000000000000000000000000000000000000000000000000000000000000000000000000000000000000000000000000000000000000000000000000000000000000000 .
b1101110111011101010001000100010000000000000000000000000000000000000000000000000000000000000000000000000000000000000000000000000000000000000000000000000000000000000000000000000000000000000000000000000000000000000000000000000000000000000000000000000000000000 =
#510000
0+
#515000
1+
#516000
11
#520000
0+
#525000
b11111111 P
b1111111111111111 K
b1110111011101110010101010101010100000000000000000000000000000000000000000000000000000000000000000000000000000000000000000000000000000000000000000000000000000000000000000000000000000000000000000000000000000000000000000000000000000000000000000000000000000000 M
b1101110111011101010001000100010000000000000000000000000000000000000000000000000000000000000000000000000000000000000000000000000000000000000000000000000000000000000000000000000000000000000000000000000000000000000000000000000000000000000000000000000000000000 O
b1 Q
1+
#526000
01
#530000
0+
#535000
b10 Q
b1 #
b1 R
1+
#540000
0+
#545000
b11 Q
b10 #
b10 R
1+
#550000
0+
#555000
b100 Q
b11 #
b11 R
1+
#560000
0+
#565000
b101 Q
b100 #
b100 R
1+
#570000
0+
#575000
b110 Q
1"
b101 !
b101 S
b1110111011101110010101010101010100000000000000000000000000000000000000000000000000000000000000000000000000000000000000000000000000000000000000000000000000000000000000000000000000000000000000000000000000000000000000000000000000000000000000000000000000000000 N
b101 #
b101 R
1+
#580000
0+
#585000
b0 Q
1'
b110 #
b110 R
1+
#590000
0+
#595000
0"
0'
b0 #
b0 R
b101 3
1+
#596000
b110 9
#600000
0+
#605000
1+
#607000
b1111111 *
b1111111 :
b1111111111111111011001100110011000000000000000000000000000000000000000000000000000000000000000000000000000000000000000000000000000000000000000000000000000000000000000000000000000000000000000000000000000000000000000000000000000000000000000000000000000000000 -
b1111111111111111011001100110011000000000000000000000000000000000000000000000000000000000000000000000000000000000000000000000000000000000000000000000000000000000000000000000000000000000000000000000000000000000000000000000000000000000000000000000000000000000 <
b1110111011101110010101010101010100000000000000000000000000000000000000000000000000000000000000000000000000000000000000000000000000000000000000000000000000000000000000000000000000000000000000000000000000000000000000000000000000000000000000000000000000000000 .
b1110111011101110010101010101010100000000000000000000000000000000000000000000000000000000000000000000000000000000000000000000000000000000000000000000000000000000000000000000000000000000000000000000000000000000000000000000000000000000000000000000000000000000 =
#610000
0+
#615000
1+
#616000
11
#620000
0+
#625000
b1111111 K
b1111111111111111011001100110011000000000000000000000000000000000000000000000000000000000000000000000000000000000000000000000000000000000000000000000000000000000000000000000000000000000000000000000000000000000000000000000000000000000000000000000000000000000 M
b1110111011101110010101010101010100000000000000000000000000000000000000000000000000000000000000000000000000000000000000000000000000000000000000000000000000000000000000000000000000000000000000000000000000000000000000000000000000000000000000000000000000000000 O
b1 Q
1+
#626000
01
#630000
0+
#635000
b10 Q
b1 #
b1 R
1+
#640000
0+
#645000
b11 Q
b10 #
b10 R
1+
#650000
0+
#655000
b100 Q
b11 #
b11 R
1+
#660000
0+
#665000
b1010 Q
1$
b100 #
b100 R
1+
#670000
0+
#675000
b0 Q
1'
b1010 #
b1010 R
1+
#680000
0+
#685000
0$
0'
b0 #
b0 R
16
07
1+
#686000
b111 9
#690000
0+
#695000
1+
#697000
b0 /
b0 >
b1111111111111111 *
b1111111111111111 :
b0 -
b0 <
#700000
0+
#705000
1+
#706000
11
#710000
0+
#715000
b0 P
b1111111111111111 K
b0 M
b1 Q
1+
#716000
01
#720000
0+
#725000
b10 Q
b1 #
b1 R
1+
#730000
0+
#735000
b11 Q
b10 #
b10 R
1+
#740000
0+
#745000
b1001 Q
1%
b11 #
b11 R
1+
#750000
0+
#755000
b0 Q
1'
b1001 #
b1001 R
1+
#760000
0+
#765000
0%
0'
b0 #
b0 R
06
15
1+
#766000
b1000 9
#770000
0+
#775000
1+
